[
  {
    "zip": 6687864,
    "pos": "32.0464016103675,34.7760457330952",
    "n": 1
  },
  {
    "zip": 6687865,
    "pos": "32.0465706706402,34.7761817452621",
    "n": 2
  },
  {
    "zip": 6680072,
    "pos": "32.0464958403917,34.7758864201143",
    "entries": [
      {
        "entry": "ב",
        "zip": 6680073,
        "pos": "32.0464958403917,34.7758864201143"
      },
      {
        "entry": "",
        "zip": 6687866,
        "pos": "32.0464958403917,34.7758864201143"
      }
    ],
    "n": 3
  },
  {
    "zip": 6680074,
    "pos": "32.0466699242322,34.7759280886627",
    "entries": [
      {
        "entry": "ב",
        "zip": 6680075,
        "pos": "32.0466699242322,34.7759280886627"
      },
      {
        "entry": "",
        "zip": 6687867,
        "pos": "32.0466699242322,34.7759280886627"
      }
    ],
    "n": 4
  },
  {
    "zip": 6680076,
    "pos": "32.0466336678766,34.7755403483049",
    "entries": [
      {
        "entry": "ב",
        "zip": 6680077,
        "pos": "32.0466336678766,34.7755403483049"
      },
      {
        "entry": "",
        "zip": 6687868,
        "pos": "32.0466336678766,34.7755403483049"
      }
    ],
    "n": 5
  },
  {
    "zip": 6680078,
    "pos": "32.0467259927454,34.7757687062518",
    "entries": [
      {
        "entry": "ב",
        "zip": 6680079,
        "pos": "32.0467259927454,34.7757687062518"
      },
      {
        "entry": "",
        "zip": 6687869,
        "pos": "32.0467259927454,34.7757687062518"
      }
    ],
    "n": 6
  },
  {
    "zip": 6680080,
    "pos": "32.0468076974259,34.7755712666134",
    "entries": [
      {
        "entry": "ב",
        "zip": 6680081,
        "pos": "32.0468076974259,34.7755712666134"
      },
      {
        "entry": "",
        "zip": 6687870,
        "pos": "32.0468076974259,34.7755712666134"
      }
    ],
    "n": 8
  }
]