[
  {
    "zip": 2304614,
    "pos": "32.6812036019427,35.2407491757972",
    "entries": [
      {
        "entry": "א",
        "zip": 2304615,
        "pos": "32.6812036019427,35.2407491757972"
      },
      {
        "entry": "ב",
        "zip": 2304616,
        "pos": "32.6812036019427,35.2407491757972"
      }
    ],
    "n": 2
  },
  {
    "zip": 2304617,
    "pos": "32.6816096190915,35.2395506333845",
    "entries": [
      {
        "entry": "א",
        "zip": 2304618,
        "pos": "32.6816096190915,35.2395506333845"
      },
      {
        "entry": "ב",
        "zip": 2304619,
        "pos": "32.6816096190915,35.2395506333845"
      }
    ],
    "n": 3
  },
  {
    "zip": 2304620,
    "pos": "32.6811094241767,35.2409115840525",
    "entries": [
      {
        "entry": "א",
        "zip": 2304645,
        "pos": "32.6811094241767,35.2409115840525"
      },
      {
        "entry": "ב",
        "zip": 2304646,
        "pos": "32.6811094241767,35.2409115840525"
      }
    ],
    "n": 4
  },
  {
    "zip": 2304621,
    "pos": "32.6813689293421,35.2400502873832",
    "entries": [
      {
        "entry": "א",
        "zip": 2304622,
        "pos": "32.6813689293421,35.2400502873832"
      },
      {
        "entry": "ב",
        "zip": 2304623,
        "pos": "32.6813689293421,35.2400502873832"
      }
    ],
    "n": 5
  },
  {
    "zip": 2304624,
    "pos": "32.6810045802037,35.2412359486837",
    "entries": [
      {
        "entry": "א",
        "zip": 2304625,
        "pos": "32.6810045802037,35.2412359486837"
      },
      {
        "entry": "ב",
        "zip": 2304626,
        "pos": "32.6810045802037,35.2412359486837"
      }
    ],
    "n": 6
  },
  {
    "zip": 2304627,
    "pos": "32.6806425219448,35.241600142272",
    "entries": [
      {
        "entry": "א",
        "zip": 2304628,
        "pos": "32.6806425219448,35.241600142272"
      },
      {
        "entry": "ב",
        "zip": 2304629,
        "pos": "32.6806425219448,35.241600142272"
      }
    ],
    "n": 8
  },
  {
    "zip": 2304630,
    "pos": "32.681904060273,35.2405575164789",
    "entries": [
      {
        "entry": "א",
        "zip": 2304631,
        "pos": "32.681904060273,35.2405575164789"
      },
      {
        "entry": "ב",
        "zip": 2304632,
        "pos": "32.681904060273,35.2405575164789"
      }
    ],
    "n": 9
  },
  {
    "zip": 2304633,
    "pos": "32.6819350312676,35.241150757981",
    "entries": [
      {
        "entry": "א",
        "zip": 2304634,
        "pos": "32.6819350312676,35.241150757981"
      },
      {
        "entry": "ב",
        "zip": 2304635,
        "pos": "32.6819350312676,35.241150757981"
      }
    ],
    "n": 11
  },
  {
    "zip": 2304647,
    "pos": "32.681663,35.240931",
    "n": 12
  },
  {
    "zip": 2304636,
    "pos": "32.6815995548571,35.2415637604648",
    "entries": [
      {
        "entry": "א",
        "zip": 2304637,
        "pos": "32.6815995548571,35.2415637604648"
      },
      {
        "entry": "ב",
        "zip": 2304638,
        "pos": "32.6815995548571,35.2415637604648"
      }
    ],
    "n": 13
  }
]