[
  {
    "zip": 9952301,
    "pos": "31.7409555589085,34.9891154592416",
    "entries": [
      {
        "entry": "א",
        "zip": 9952302,
        "pos": "31.7409555589085,34.9891154592416"
      },
      {
        "entry": "ב",
        "zip": 9952303,
        "pos": "31.7409555589085,34.9891154592416"
      },
      {
        "entry": "ג",
        "zip": 9952304,
        "pos": "31.7409555589085,34.9891154592416"
      }
    ],
    "n": 1
  },
  {
    "zip": 9952305,
    "pos": "31.741189154038,34.9881255328277",
    "entries": [
      {
        "entry": "א",
        "zip": 9952306,
        "pos": "31.741189154038,34.9881255328277"
      },
      {
        "entry": "ב",
        "zip": 9952307,
        "pos": "31.741189154038,34.9881255328277"
      }
    ],
    "n": 3
  },
  {
    "zip": 9952308,
    "pos": "31.7409112571882,34.988428080163",
    "n": 5
  },
  {
    "zip": 9952311,
    "pos": "31.74095436,34.99014067",
    "n": 7
  },
  {
    "zip": 9952313,
    "pos": "31.7411272144124,34.9889959336126",
    "entries": [
      {
        "entry": "א",
        "zip": 9952314,
        "pos": "31.7411272144124,34.9889959336126"
      },
      {
        "entry": "ב",
        "zip": 9952315,
        "pos": "31.7411272144124,34.9889959336126"
      }
    ],
    "n": 9
  },
  {
    "zip": 9952316,
    "pos": "31.7406869227244,34.9867892486789",
    "entries": [
      {
        "entry": "א",
        "zip": 9952317,
        "pos": "31.7406869227244,34.9867892486789"
      },
      {
        "entry": "ב",
        "zip": 9952318,
        "pos": "31.7406869227244,34.9867892486789"
      }
    ],
    "n": 11
  },
  {
    "zip": 9952319,
    "pos": "31.7408177483017,34.9871876745827",
    "entries": [
      {
        "entry": "א",
        "zip": 9952320,
        "pos": "31.7408177483017,34.9871876745827"
      },
      {
        "entry": "ב",
        "zip": 9952321,
        "pos": "31.7408177483017,34.9871876745827"
      }
    ],
    "n": 13
  },
  {
    "zip": 9952322,
    "pos": "31.7409757520893,34.9875668391275",
    "entries": [
      {
        "entry": "א",
        "zip": 9952323,
        "pos": "31.7409757520893,34.9875668391275"
      },
      {
        "entry": "ב",
        "zip": 9952324,
        "pos": "31.7409757520893,34.9875668391275"
      }
    ],
    "n": 15
  },
  {
    "zip": 9952325,
    "pos": "31.7407952907383,34.9876385463332",
    "entries": [
      {
        "entry": "א",
        "zip": 9952326,
        "pos": "31.7407952907383,34.9876385463332"
      },
      {
        "entry": "ב",
        "zip": 9952327,
        "pos": "31.7407952907383,34.9876385463332"
      }
    ],
    "n": 17
  },
  {
    "zip": 9952328,
    "pos": "31.7411965831785,34.9872661349081",
    "entries": [
      {
        "entry": "א",
        "zip": 9952329,
        "pos": "31.7411965831785,34.9872661349081"
      },
      {
        "entry": "ב",
        "zip": 9952330,
        "pos": "31.7411965831785,34.9872661349081"
      }
    ],
    "n": 19
  },
  {
    "zip": 9952331,
    "pos": "31.7412826657724,34.986724658689",
    "n": 21
  },
  {
    "zip": 9952332,
    "pos": "31.7417496606588,34.9855662469102",
    "n": 23
  }
]