[
  {
    "zip": 7176568,
    "pos": "31.8860924448168,35.0096652175419",
    "entries": [
      {
        "entry": "א",
        "zip": 7177363,
        "pos": "31.8860924448168,35.0096652175419"
      },
      {
        "entry": "ב",
        "zip": 7177364,
        "pos": "31.8860924448168,35.0096652175419"
      },
      {
        "entry": "ג",
        "zip": 7177365,
        "pos": "31.8860924448168,35.0096652175419"
      },
      {
        "entry": "ד",
        "zip": 7177366,
        "pos": "31.8860924448168,35.0096652175419"
      },
      {
        "entry": "ה",
        "zip": 7177367,
        "pos": "31.8860924448168,35.0096652175419"
      }
    ],
    "n": 1
  },
  {
    "zip": 7176569,
    "pos": "31.8866116973489,35.0097639953611",
    "entries": [
      {
        "entry": "א",
        "zip": 7178235,
        "pos": "31.8866116973489,35.0097639953611"
      },
      {
        "entry": "ב",
        "zip": 7178236,
        "pos": "31.8866116973489,35.0097639953611"
      }
    ],
    "n": 3
  },
  {
    "zip": 7176570,
    "pos": "31.8868882383691,35.0097655012891",
    "entries": [
      {
        "entry": "א",
        "zip": 7178237,
        "pos": "31.8868882383691,35.0097655012891"
      },
      {
        "entry": "ב",
        "zip": 7178238,
        "pos": "31.8868882383691,35.0097655012891"
      }
    ],
    "n": 5
  },
  {
    "zip": 7176571,
    "pos": "31.8871622753549,35.0097130446627",
    "entries": [
      {
        "entry": "א",
        "zip": 7178239,
        "pos": "31.8871622753549,35.0097130446627"
      },
      {
        "entry": "ב",
        "zip": 7178240,
        "pos": "31.8871622753549,35.0097130446627"
      }
    ],
    "n": 7
  },
  {
    "zip": 7176572,
    "pos": "31.8874202898237,35.0096377665129",
    "entries": [
      {
        "entry": "א",
        "zip": 7178241,
        "pos": "31.8874202898237,35.0096377665129"
      },
      {
        "entry": "ב",
        "zip": 7178242,
        "pos": "31.8874202898237,35.0096377665129"
      }
    ],
    "n": 9
  },
  {
    "zip": 7176573,
    "pos": "31.8876682076291,35.0095149653746",
    "entries": [
      {
        "entry": "א",
        "zip": 7178243,
        "pos": "31.8876682076291,35.0095149653746"
      },
      {
        "entry": "ב",
        "zip": 7178244,
        "pos": "31.8876682076291,35.0095149653746"
      }
    ],
    "n": 11
  },
  {
    "zip": 7176574,
    "pos": "31.887904735487,35.0093899488953",
    "entries": [
      {
        "entry": "א",
        "zip": 7178245,
        "pos": "31.887904735487,35.0093899488953"
      },
      {
        "entry": "ב",
        "zip": 7178246,
        "pos": "31.887904735487,35.0093899488953"
      }
    ],
    "n": 13
  },
  {
    "zip": 7176575,
    "pos": "31.8881361654003,35.0092192376084",
    "entries": [
      {
        "entry": "א",
        "zip": 7178247,
        "pos": "31.8881361654003,35.0092192376084"
      },
      {
        "entry": "ב",
        "zip": 7178248,
        "pos": "31.8881361654003,35.0092192376084"
      }
    ],
    "n": 15
  },
  {
    "zip": 7176576,
    "pos": "31.8883406798821,35.0090260431693",
    "entries": [
      {
        "entry": "א",
        "zip": 7178249,
        "pos": "31.8883406798821,35.0090260431693"
      },
      {
        "entry": "ב",
        "zip": 7178250,
        "pos": "31.8883406798821,35.0090260431693"
      }
    ],
    "n": 17
  }
]