[
  {
    "zip": 8428650,
    "pos": "31.2485041301218,34.7889728207013",
    "entries": [
      {
        "entry": "א",
        "zip": 8428651,
        "pos": "31.2485041301218,34.7889728207013"
      },
      {
        "entry": "ב",
        "zip": 8428652,
        "pos": "31.2485041301218,34.7889728207013"
      },
      {
        "entry": "ג",
        "zip": 8428653,
        "pos": "31.2485041301218,34.7889728207013"
      }
    ],
    "n": 1
  },
  {
    "zip": 8428654,
    "pos": "31.2485661178527,34.7887301283325",
    "n": 2
  },
  {
    "zip": 8428655,
    "pos": "31.248333471545,34.7887858044346",
    "entries": [
      {
        "entry": "א",
        "zip": 8428656,
        "pos": "31.248333471545,34.7887858044346"
      },
      {
        "entry": "ב",
        "zip": 8428657,
        "pos": "31.248333471545,34.7887858044346"
      },
      {
        "entry": "ג",
        "zip": 8428658,
        "pos": "31.248333471545,34.7887858044346"
      }
    ],
    "n": 3
  },
  {
    "zip": 8428659,
    "pos": "31.2481887799614,34.7884481108291",
    "n": 4
  },
  {
    "zip": 8428660,
    "pos": "31.2481689817092,34.7885164292508",
    "entries": [
      {
        "entry": "א",
        "zip": 8428661,
        "pos": "31.2481689817092,34.7885164292508"
      },
      {
        "entry": "ב",
        "zip": 8428662,
        "pos": "31.2481689817092,34.7885164292508"
      },
      {
        "entry": "ג",
        "zip": 8428663,
        "pos": "31.2481689817092,34.7885164292508"
      }
    ],
    "n": 5
  },
  {
    "zip": 8428001,
    "pos": "31.2479168644749,34.7881559980011",
    "entries": [
      {
        "entry": "א",
        "zip": 8428002,
        "pos": "31.2479168644749,34.7881559980011"
      },
      {
        "entry": "ב",
        "zip": 8428003,
        "pos": "31.2479168644749,34.7881559980011"
      },
      {
        "entry": "ג",
        "zip": 8428004,
        "pos": "31.2479168644749,34.7881559980011"
      }
    ],
    "n": 6
  },
  {
    "zip": 8428664,
    "pos": "31.2480058065992,34.7884288569713",
    "entries": [
      {
        "entry": "א",
        "zip": 8428665,
        "pos": "31.2480058065992,34.7884288569713"
      },
      {
        "entry": "ב",
        "zip": 8428666,
        "pos": "31.2480058065992,34.7884288569713"
      },
      {
        "entry": "ג",
        "zip": 8428667,
        "pos": "31.2480058065992,34.7884288569713"
      }
    ],
    "n": 7
  },
  {
    "zip": 8428005,
    "pos": "31.2477432216176,34.7879604764553",
    "entries": [
      {
        "entry": "א",
        "zip": 8428006,
        "pos": "31.2477432216176,34.7879604764553"
      },
      {
        "entry": "ב",
        "zip": 8428007,
        "pos": "31.2477432216176,34.7879604764553"
      },
      {
        "entry": "ג",
        "zip": 8428008,
        "pos": "31.2477432216176,34.7879604764553"
      }
    ],
    "n": 8
  },
  {
    "zip": 8428009,
    "pos": "31.247659819413,34.7885187379391",
    "entries": [
      {
        "entry": "א",
        "zip": 8428010,
        "pos": "31.247659819413,34.7885187379391"
      },
      {
        "entry": "ב",
        "zip": 8428011,
        "pos": "31.247659819413,34.7885187379391"
      },
      {
        "entry": "ג",
        "zip": 8428012,
        "pos": "31.247659819413,34.7885187379391"
      }
    ],
    "n": 9
  },
  {
    "zip": 8428013,
    "pos": "31.2476211524914,34.7877380849753",
    "entries": [
      {
        "entry": "א",
        "zip": 8428014,
        "pos": "31.2476211524914,34.7877380849753"
      },
      {
        "entry": "ב",
        "zip": 8428015,
        "pos": "31.2476211524914,34.7877380849753"
      },
      {
        "entry": "ג",
        "zip": 8428016,
        "pos": "31.2476211524914,34.7877380849753"
      }
    ],
    "n": 10
  },
  {
    "zip": 8428017,
    "pos": "31.2476207705733,34.7881589511706",
    "entries": [
      {
        "entry": "א",
        "zip": 8428018,
        "pos": "31.2476207705733,34.7881589511706"
      },
      {
        "entry": "ב",
        "zip": 8428019,
        "pos": "31.2476207705733,34.7881589511706"
      },
      {
        "entry": "ג",
        "zip": 8428020,
        "pos": "31.2476207705733,34.7881589511706"
      }
    ],
    "n": 11
  },
  {
    "zip": 8428021,
    "pos": "31.2474780879211,34.787491335084",
    "entries": [
      {
        "entry": "א",
        "zip": 8428022,
        "pos": "31.2474780879211,34.787491335084"
      },
      {
        "entry": "ב",
        "zip": 8428023,
        "pos": "31.2474780879211,34.787491335084"
      },
      {
        "entry": "ג",
        "zip": 8428024,
        "pos": "31.2474780879211,34.787491335084"
      }
    ],
    "n": 12
  },
  {
    "zip": 8428025,
    "pos": "31.2474760264998,34.7879873609618",
    "entries": [
      {
        "entry": "א",
        "zip": 8428026,
        "pos": "31.2474760264998,34.7879873609618"
      },
      {
        "entry": "ב",
        "zip": 8428027,
        "pos": "31.2474760264998,34.7879873609618"
      },
      {
        "entry": "ג",
        "zip": 8428028,
        "pos": "31.2474760264998,34.7879873609618"
      }
    ],
    "n": 13
  },
  {
    "zip": 8428029,
    "pos": "31.2473573714917,34.7872991669399",
    "entries": [
      {
        "entry": "א",
        "zip": 8428030,
        "pos": "31.2473573714917,34.7872991669399"
      },
      {
        "entry": "ב",
        "zip": 8428031,
        "pos": "31.2473573714917,34.7872991669399"
      },
      {
        "entry": "ג",
        "zip": 8428032,
        "pos": "31.2473573714917,34.7872991669399"
      }
    ],
    "n": 14
  },
  {
    "zip": 8428033,
    "pos": "31.2473494306581,34.7877866476943",
    "entries": [
      {
        "entry": "א",
        "zip": 8428034,
        "pos": "31.2473494306581,34.7877866476943"
      },
      {
        "entry": "ב",
        "zip": 8428035,
        "pos": "31.2473494306581,34.7877866476943"
      },
      {
        "entry": "ג",
        "zip": 8428036,
        "pos": "31.2473494306581,34.7877866476943"
      }
    ],
    "n": 15
  },
  {
    "zip": 8428037,
    "pos": "31.2472323486319,34.7870765729053",
    "entries": [
      {
        "entry": "א",
        "zip": 8428038,
        "pos": "31.2472323486319,34.7870765729053"
      },
      {
        "entry": "ב",
        "zip": 8428039,
        "pos": "31.2472323486319,34.7870765729053"
      },
      {
        "entry": "ג",
        "zip": 8428040,
        "pos": "31.2472323486319,34.7870765729053"
      }
    ],
    "n": 16
  },
  {
    "zip": 8428041,
    "pos": "31.2472384373019,34.7875786534909",
    "entries": [
      {
        "entry": "א",
        "zip": 8428042,
        "pos": "31.2472384373019,34.7875786534909"
      },
      {
        "entry": "ב",
        "zip": 8428043,
        "pos": "31.2472384373019,34.7875786534909"
      },
      {
        "entry": "ג",
        "zip": 8428044,
        "pos": "31.2472384373019,34.7875786534909"
      }
    ],
    "n": 17
  },
  {
    "zip": 8428045,
    "pos": "31.2471910263921,34.7867317218534",
    "entries": [
      {
        "entry": "א",
        "zip": 8428046,
        "pos": "31.2471910263921,34.7867317218534"
      },
      {
        "entry": "ב",
        "zip": 8428047,
        "pos": "31.2471910263921,34.7867317218534"
      },
      {
        "entry": "ג",
        "zip": 8428048,
        "pos": "31.2471910263921,34.7867317218534"
      }
    ],
    "n": 18
  },
  {
    "zip": 8428049,
    "pos": "31.2471314361587,34.7873486370582",
    "entries": [
      {
        "entry": "א",
        "zip": 8428050,
        "pos": "31.2471314361587,34.7873486370582"
      },
      {
        "entry": "ב",
        "zip": 8428051,
        "pos": "31.2471314361587,34.7873486370582"
      },
      {
        "entry": "ג",
        "zip": 8428052,
        "pos": "31.2471314361587,34.7873486370582"
      }
    ],
    "n": 19
  },
  {
    "zip": 8428053,
    "pos": "31.247191659991,34.7864501687785",
    "entries": [
      {
        "entry": "א",
        "zip": 8428054,
        "pos": "31.247191659991,34.7864501687785"
      },
      {
        "entry": "ב",
        "zip": 8428055,
        "pos": "31.247191659991,34.7864501687785"
      },
      {
        "entry": "ג",
        "zip": 8428056,
        "pos": "31.247191659991,34.7864501687785"
      }
    ],
    "n": 20
  },
  {
    "zip": 8428057,
    "pos": "31.2469598646678,34.7871809135181",
    "entries": [
      {
        "entry": "א",
        "zip": 8428058,
        "pos": "31.2469598646678,34.7871809135181"
      },
      {
        "entry": "ב",
        "zip": 8428059,
        "pos": "31.2469598646678,34.7871809135181"
      },
      {
        "entry": "ג",
        "zip": 8428060,
        "pos": "31.2469598646678,34.7871809135181"
      }
    ],
    "n": 21
  },
  {
    "zip": 8428061,
    "pos": "31.2472478693091,34.7862190975811",
    "entries": [
      {
        "entry": "א",
        "zip": 8428062,
        "pos": "31.2472478693091,34.7862190975811"
      },
      {
        "entry": "ב",
        "zip": 8428063,
        "pos": "31.2472478693091,34.7862190975811"
      },
      {
        "entry": "ג",
        "zip": 8428064,
        "pos": "31.2472478693091,34.7862190975811"
      }
    ],
    "n": 22
  },
  {
    "zip": 8428065,
    "pos": "31.2470052807809,34.786867189363",
    "entries": [
      {
        "entry": "א",
        "zip": 8428066,
        "pos": "31.2470052807809,34.786867189363"
      },
      {
        "entry": "ב",
        "zip": 8428067,
        "pos": "31.2470052807809,34.786867189363"
      },
      {
        "entry": "ג",
        "zip": 8428068,
        "pos": "31.2470052807809,34.786867189363"
      }
    ],
    "n": 23
  },
  {
    "zip": 8428069,
    "pos": "31.2473692005478,34.785972324204",
    "entries": [
      {
        "entry": "א",
        "zip": 8428070,
        "pos": "31.2473692005478,34.785972324204"
      },
      {
        "entry": "ב",
        "zip": 8428071,
        "pos": "31.2473692005478,34.785972324204"
      },
      {
        "entry": "ג",
        "zip": 8428072,
        "pos": "31.2473692005478,34.785972324204"
      }
    ],
    "n": 24
  },
  {
    "zip": 8428073,
    "pos": "31.2469125145103,34.7866353763837",
    "entries": [
      {
        "entry": "א",
        "zip": 8428074,
        "pos": "31.2469125145103,34.7866353763837"
      },
      {
        "entry": "ב",
        "zip": 8428075,
        "pos": "31.2469125145103,34.7866353763837"
      },
      {
        "entry": "ג",
        "zip": 8428076,
        "pos": "31.2469125145103,34.7866353763837"
      }
    ],
    "n": 25
  },
  {
    "zip": 8428077,
    "pos": "31.2475579956149,34.7857795707902",
    "entries": [
      {
        "entry": "א",
        "zip": 8428078,
        "pos": "31.2475579956149,34.7857795707902"
      },
      {
        "entry": "ב",
        "zip": 8428079,
        "pos": "31.2475579956149,34.7857795707902"
      },
      {
        "entry": "ג",
        "zip": 8428080,
        "pos": "31.2475579956149,34.7857795707902"
      }
    ],
    "n": 26
  },
  {
    "zip": 8428081,
    "pos": "31.2470331336667,34.7863837670857",
    "entries": [
      {
        "entry": "א",
        "zip": 8428082,
        "pos": "31.2470331336667,34.7863837670857"
      },
      {
        "entry": "ב",
        "zip": 8428083,
        "pos": "31.2470331336667,34.7863837670857"
      },
      {
        "entry": "ג",
        "zip": 8428084,
        "pos": "31.2470331336667,34.7863837670857"
      }
    ],
    "n": 27
  },
  {
    "zip": 8428085,
    "pos": "31.2477482474873,34.7856550936283",
    "entries": [
      {
        "entry": "א",
        "zip": 8428086,
        "pos": "31.2477482474873,34.7856550936283"
      },
      {
        "entry": "ב",
        "zip": 8428087,
        "pos": "31.2477482474873,34.7856550936283"
      },
      {
        "entry": "ג",
        "zip": 8428088,
        "pos": "31.2477482474873,34.7856550936283"
      }
    ],
    "n": 28
  },
  {
    "zip": 8428089,
    "pos": "31.2470613663959,34.7861445673398",
    "entries": [
      {
        "entry": "א",
        "zip": 8428090,
        "pos": "31.2470613663959,34.7861445673398"
      },
      {
        "entry": "ב",
        "zip": 8428091,
        "pos": "31.2470613663959,34.7861445673398"
      },
      {
        "entry": "ג",
        "zip": 8428092,
        "pos": "31.2470613663959,34.7861445673398"
      }
    ],
    "n": 29
  },
  {
    "zip": 8428101,
    "pos": "31.2479650883682,34.7855104353191",
    "entries": [
      {
        "entry": "א",
        "zip": 8428102,
        "pos": "31.2479650883682,34.7855104353191"
      },
      {
        "entry": "ב",
        "zip": 8428103,
        "pos": "31.2479650883682,34.7855104353191"
      },
      {
        "entry": "ג",
        "zip": 8428104,
        "pos": "31.2479650883682,34.7855104353191"
      }
    ],
    "n": 30
  },
  {
    "zip": 8428093,
    "pos": "31.2471718637988,34.7859418451471",
    "entries": [
      {
        "entry": "א",
        "zip": 8428094,
        "pos": "31.2471718637988,34.7859418451471"
      },
      {
        "entry": "ב",
        "zip": 8428095,
        "pos": "31.2471718637988,34.7859418451471"
      },
      {
        "entry": "ג",
        "zip": 8428096,
        "pos": "31.2471718637988,34.7859418451471"
      }
    ],
    "n": 31
  },
  {
    "zip": 8428105,
    "pos": "31.2481949061561,34.7854459020313",
    "entries": [
      {
        "entry": "א",
        "zip": 8428106,
        "pos": "31.2481949061561,34.7854459020313"
      },
      {
        "entry": "ב",
        "zip": 8428107,
        "pos": "31.2481949061561,34.7854459020313"
      },
      {
        "entry": "ג",
        "zip": 8428108,
        "pos": "31.2481949061561,34.7854459020313"
      }
    ],
    "n": 32
  },
  {
    "zip": 8423901,
    "pos": "31.2472995408681,34.7857160148105",
    "entries": [
      {
        "entry": "",
        "zip": 8428097,
        "pos": "31.2472995408681,34.7857160148105"
      },
      {
        "entry": "א",
        "zip": 8428098,
        "pos": "31.2472995408681,34.7857160148105"
      },
      {
        "entry": "ב",
        "zip": 8428099,
        "pos": "31.2472995408681,34.7857160148105"
      }
    ],
    "n": 33
  },
  {
    "zip": 8428109,
    "pos": "31.2484194691199,34.7854117218456",
    "entries": [
      {
        "entry": "א",
        "zip": 8428110,
        "pos": "31.2484194691199,34.7854117218456"
      },
      {
        "entry": "ב",
        "zip": 8428111,
        "pos": "31.2484194691199,34.7854117218456"
      },
      {
        "entry": "ג",
        "zip": 8428112,
        "pos": "31.2484194691199,34.7854117218456"
      }
    ],
    "n": 34
  },
  {
    "zip": 8423902,
    "pos": "31.2474581454607,34.7855202985238",
    "entries": [
      {
        "entry": "א",
        "zip": 8423903,
        "pos": "31.2474581454607,34.7855202985238"
      },
      {
        "entry": "ב",
        "zip": 8423904,
        "pos": "31.2474581454607,34.7855202985238"
      },
      {
        "entry": "ג",
        "zip": 8423905,
        "pos": "31.2474581454607,34.7855202985238"
      }
    ],
    "n": 35
  },
  {
    "zip": 8428113,
    "pos": "31.2487802450913,34.7852389859225",
    "entries": [
      {
        "entry": "א",
        "zip": 8428114,
        "pos": "31.2487802450913,34.7852389859225"
      },
      {
        "entry": "ב",
        "zip": 8428115,
        "pos": "31.2487802450913,34.7852389859225"
      },
      {
        "entry": "ג",
        "zip": 8428116,
        "pos": "31.2487802450913,34.7852389859225"
      }
    ],
    "n": 36
  },
  {
    "zip": 8423906,
    "pos": "31.2476387959891,34.7854095607752",
    "entries": [
      {
        "entry": "א",
        "zip": 8423907,
        "pos": "31.2476387959891,34.7854095607752"
      },
      {
        "entry": "ב",
        "zip": 8423908,
        "pos": "31.2476387959891,34.7854095607752"
      },
      {
        "entry": "ג",
        "zip": 8423909,
        "pos": "31.2476387959891,34.7854095607752"
      }
    ],
    "n": 37
  },
  {
    "zip": 8428205,
    "pos": "31.2489656882115,34.78505059328",
    "entries": [
      {
        "entry": "א",
        "zip": 8428206,
        "pos": "31.2489656882115,34.78505059328"
      },
      {
        "entry": "ב",
        "zip": 8428207,
        "pos": "31.2489656882115,34.78505059328"
      },
      {
        "entry": "ג",
        "zip": 8428208,
        "pos": "31.2489656882115,34.78505059328"
      }
    ],
    "n": 38
  },
  {
    "zip": 8428117,
    "pos": "31.2478518063967,34.7853064606057",
    "entries": [
      {
        "entry": "א",
        "zip": 8428118,
        "pos": "31.2478518063967,34.7853064606057"
      },
      {
        "entry": "ב",
        "zip": 8428119,
        "pos": "31.2478518063967,34.7853064606057"
      },
      {
        "entry": "ג",
        "zip": 8428120,
        "pos": "31.2478518063967,34.7853064606057"
      }
    ],
    "n": 39
  },
  {
    "zip": 8428209,
    "pos": "31.2492336845094,34.7849341716148",
    "entries": [
      {
        "entry": "א",
        "zip": 8428210,
        "pos": "31.2492336845094,34.7849341716148"
      },
      {
        "entry": "ב",
        "zip": 8428211,
        "pos": "31.2492336845094,34.7849341716148"
      },
      {
        "entry": "ג",
        "zip": 8428212,
        "pos": "31.2492336845094,34.7849341716148"
      }
    ],
    "n": 40
  },
  {
    "zip": 8428121,
    "pos": "31.248043613316,34.7852131588014",
    "entries": [
      {
        "entry": "א",
        "zip": 8428122,
        "pos": "31.248043613316,34.7852131588014"
      },
      {
        "entry": "ב",
        "zip": 8428123,
        "pos": "31.248043613316,34.7852131588014"
      },
      {
        "entry": "ג",
        "zip": 8428124,
        "pos": "31.248043613316,34.7852131588014"
      }
    ],
    "n": 41
  },
  {
    "zip": 8428213,
    "pos": "31.2494325312845,34.7848646111417",
    "entries": [
      {
        "entry": "א",
        "zip": 8428214,
        "pos": "31.2494325312845,34.7848646111417"
      },
      {
        "entry": "ב",
        "zip": 8428215,
        "pos": "31.2494325312845,34.7848646111417"
      },
      {
        "entry": "ג",
        "zip": 8428216,
        "pos": "31.2494325312845,34.7848646111417"
      }
    ],
    "n": 42
  },
  {
    "zip": 8428125,
    "pos": "31.2482874689358,34.7850393459534",
    "entries": [
      {
        "entry": "א",
        "zip": 8428126,
        "pos": "31.2482874689358,34.7850393459534"
      },
      {
        "entry": "ב",
        "zip": 8428127,
        "pos": "31.2482874689358,34.7850393459534"
      },
      {
        "entry": "ג",
        "zip": 8428128,
        "pos": "31.2482874689358,34.7850393459534"
      }
    ],
    "n": 43
  },
  {
    "zip": 8428217,
    "pos": "31.2496621664822,34.7849415807841",
    "entries": [
      {
        "entry": "א",
        "zip": 8428218,
        "pos": "31.2496621664822,34.7849415807841"
      },
      {
        "entry": "ב",
        "zip": 8428219,
        "pos": "31.2496621664822,34.7849415807841"
      },
      {
        "entry": "ג",
        "zip": 8428220,
        "pos": "31.2496621664822,34.7849415807841"
      }
    ],
    "n": 44
  },
  {
    "zip": 8428129,
    "pos": "31.2486834749519,34.7848567678223",
    "entries": [
      {
        "entry": "א",
        "zip": 8428130,
        "pos": "31.2486834749519,34.7848567678223"
      },
      {
        "entry": "ב",
        "zip": 8428131,
        "pos": "31.2486834749519,34.7848567678223"
      },
      {
        "entry": "ג",
        "zip": 8428132,
        "pos": "31.2486834749519,34.7848567678223"
      }
    ],
    "n": 45
  },
  {
    "zip": 8428221,
    "pos": "31.2499222089483,34.7849678403944",
    "entries": [
      {
        "entry": "א",
        "zip": 8428222,
        "pos": "31.2499222089483,34.7849678403944"
      },
      {
        "entry": "ב",
        "zip": 8428223,
        "pos": "31.2499222089483,34.7849678403944"
      },
      {
        "entry": "ג",
        "zip": 8428224,
        "pos": "31.2499222089483,34.7849678403944"
      }
    ],
    "n": 46
  },
  {
    "zip": 8428225,
    "pos": "31.2488906234258,34.7848890913034",
    "entries": [
      {
        "entry": "א",
        "zip": 8428226,
        "pos": "31.2488906234258,34.7848890913034"
      },
      {
        "entry": "ב",
        "zip": 8428227,
        "pos": "31.2488906234258,34.7848890913034"
      },
      {
        "entry": "ג",
        "zip": 8428228,
        "pos": "31.2488906234258,34.7848890913034"
      }
    ],
    "n": 47
  },
  {
    "zip": 8428229,
    "pos": "31.2501257826596,34.7850661055207",
    "entries": [
      {
        "entry": "א",
        "zip": 8428230,
        "pos": "31.2501257826596,34.7850661055207"
      },
      {
        "entry": "ב",
        "zip": 8428231,
        "pos": "31.2501257826596,34.7850661055207"
      },
      {
        "entry": "ג",
        "zip": 8428232,
        "pos": "31.2501257826596,34.7850661055207"
      }
    ],
    "n": 48
  },
  {
    "zip": 8428233,
    "pos": "31.2490977256746,34.7847911765006",
    "entries": [
      {
        "entry": "א",
        "zip": 8428234,
        "pos": "31.2490977256746,34.7847911765006"
      },
      {
        "entry": "ב",
        "zip": 8428235,
        "pos": "31.2490977256746,34.7847911765006"
      },
      {
        "entry": "ג",
        "zip": 8428236,
        "pos": "31.2490977256746,34.7847911765006"
      }
    ],
    "n": 49
  },
  {
    "zip": 8428237,
    "pos": "31.2502805130058,34.7852972206575",
    "entries": [
      {
        "entry": "א",
        "zip": 8428238,
        "pos": "31.2502805130058,34.7852972206575"
      },
      {
        "entry": "ב",
        "zip": 8428239,
        "pos": "31.2502805130058,34.7852972206575"
      },
      {
        "entry": "ג",
        "zip": 8428240,
        "pos": "31.2502805130058,34.7852972206575"
      }
    ],
    "n": 50
  },
  {
    "zip": 8428241,
    "pos": "31.249286554868,34.7846182811471",
    "entries": [
      {
        "entry": "א",
        "zip": 8428242,
        "pos": "31.249286554868,34.7846182811471"
      },
      {
        "entry": "ב",
        "zip": 8428243,
        "pos": "31.249286554868,34.7846182811471"
      },
      {
        "entry": "ג",
        "zip": 8428244,
        "pos": "31.249286554868,34.7846182811471"
      }
    ],
    "n": 51
  },
  {
    "zip": 8428245,
    "pos": "31.2503016332674,34.7856446856931",
    "entries": [
      {
        "entry": "א",
        "zip": 8428246,
        "pos": "31.2503016332674,34.7856446856931"
      },
      {
        "entry": "ב",
        "zip": 8428247,
        "pos": "31.2503016332674,34.7856446856931"
      },
      {
        "entry": "ג",
        "zip": 8428248,
        "pos": "31.2503016332674,34.7856446856931"
      }
    ],
    "n": 52
  },
  {
    "zip": 8428249,
    "pos": "31.2494915466707,34.7845486067013",
    "entries": [
      {
        "entry": "א",
        "zip": 8428250,
        "pos": "31.2494915466707,34.7845486067013"
      },
      {
        "entry": "ב",
        "zip": 8428251,
        "pos": "31.2494915466707,34.7845486067013"
      },
      {
        "entry": "ג",
        "zip": 8428252,
        "pos": "31.2494915466707,34.7845486067013"
      }
    ],
    "n": 53
  },
  {
    "zip": 8428253,
    "pos": "31.2504373881091,34.7858502507996",
    "entries": [
      {
        "entry": "א",
        "zip": 8428254,
        "pos": "31.2504373881091,34.7858502507996"
      },
      {
        "entry": "ב",
        "zip": 8428255,
        "pos": "31.2504373881091,34.7858502507996"
      },
      {
        "entry": "ג",
        "zip": 8428256,
        "pos": "31.2504373881091,34.7858502507996"
      }
    ],
    "n": 54
  },
  {
    "zip": 8428257,
    "pos": "31.2497671923679,34.7845473115027",
    "entries": [
      {
        "entry": "א",
        "zip": 8428258,
        "pos": "31.2497671923679,34.7845473115027"
      },
      {
        "entry": "ב",
        "zip": 8428259,
        "pos": "31.2497671923679,34.7845473115027"
      },
      {
        "entry": "ג",
        "zip": 8428260,
        "pos": "31.2497671923679,34.7845473115027"
      }
    ],
    "n": 55
  },
  {
    "zip": 8428261,
    "pos": "31.2504428793344,34.7861189064866",
    "entries": [
      {
        "entry": "א",
        "zip": 8428262,
        "pos": "31.2504428793344,34.7861189064866"
      },
      {
        "entry": "ב",
        "zip": 8428263,
        "pos": "31.2504428793344,34.7861189064866"
      },
      {
        "entry": "ג",
        "zip": 8428264,
        "pos": "31.2504428793344,34.7861189064866"
      }
    ],
    "n": 56
  },
  {
    "zip": 8428265,
    "pos": "31.2499579757187,34.7847279403607",
    "entries": [
      {
        "entry": "א",
        "zip": 8428266,
        "pos": "31.2499579757187,34.7847279403607"
      },
      {
        "entry": "ב",
        "zip": 8428267,
        "pos": "31.2499579757187,34.7847279403607"
      },
      {
        "entry": "ג",
        "zip": 8428268,
        "pos": "31.2499579757187,34.7847279403607"
      }
    ],
    "n": 57
  },
  {
    "zip": 8428269,
    "pos": "31.2505277025223,34.7864031319305",
    "entries": [
      {
        "entry": "א",
        "zip": 8428270,
        "pos": "31.2505277025223,34.7864031319305"
      },
      {
        "entry": "ב",
        "zip": 8428271,
        "pos": "31.2505277025223,34.7864031319305"
      },
      {
        "entry": "ג",
        "zip": 8428272,
        "pos": "31.2505277025223,34.7864031319305"
      }
    ],
    "n": 58
  },
  {
    "zip": 8428273,
    "pos": "31.2501836437623,34.7847337008894",
    "entries": [
      {
        "entry": "א",
        "zip": 8428274,
        "pos": "31.2501836437623,34.7847337008894"
      },
      {
        "entry": "ב",
        "zip": 8428275,
        "pos": "31.2501836437623,34.7847337008894"
      },
      {
        "entry": "ג",
        "zip": 8428276,
        "pos": "31.2501836437623,34.7847337008894"
      }
    ],
    "n": 59
  },
  {
    "zip": 8428277,
    "pos": "31.2504723143563,34.786692977428",
    "entries": [
      {
        "entry": "א",
        "zip": 8428278,
        "pos": "31.2504723143563,34.786692977428"
      },
      {
        "entry": "ב",
        "zip": 8428279,
        "pos": "31.2504723143563,34.786692977428"
      },
      {
        "entry": "ג",
        "zip": 8428280,
        "pos": "31.2504723143563,34.786692977428"
      }
    ],
    "n": 60
  },
  {
    "zip": 8428281,
    "pos": "31.2503395951045,34.7850323113343",
    "entries": [
      {
        "entry": "א",
        "zip": 8428282,
        "pos": "31.2503395951045,34.7850323113343"
      },
      {
        "entry": "ב",
        "zip": 8428283,
        "pos": "31.2503395951045,34.7850323113343"
      },
      {
        "entry": "ג",
        "zip": 8428284,
        "pos": "31.2503395951045,34.7850323113343"
      }
    ],
    "n": 61
  },
  {
    "zip": 8428285,
    "pos": "31.2503761538154,34.7869960856193",
    "n": 62
  },
  {
    "zip": 8428286,
    "pos": "31.2504587895393,34.7851950906398",
    "entries": [
      {
        "entry": "א",
        "zip": 8428287,
        "pos": "31.2504587895393,34.7851950906398"
      },
      {
        "entry": "ב",
        "zip": 8428288,
        "pos": "31.2504587895393,34.7851950906398"
      },
      {
        "entry": "ג",
        "zip": 8428289,
        "pos": "31.2504587895393,34.7851950906398"
      }
    ],
    "n": 63
  },
  {
    "zip": 8428290,
    "pos": "31.2506669835439,34.7854104042314",
    "entries": [
      {
        "entry": "א",
        "zip": 8428291,
        "pos": "31.2506669835439,34.7854104042314"
      },
      {
        "entry": "ב",
        "zip": 8428292,
        "pos": "31.2506669835439,34.7854104042314"
      },
      {
        "entry": "ג",
        "zip": 8428293,
        "pos": "31.2506669835439,34.7854104042314"
      }
    ],
    "n": 65
  },
  {
    "zip": 8428294,
    "pos": "31.2507770076416,34.7856406771347",
    "entries": [
      {
        "entry": "א",
        "zip": 8428295,
        "pos": "31.2507770076416,34.7856406771347"
      },
      {
        "entry": "ב",
        "zip": 8428296,
        "pos": "31.2507770076416,34.7856406771347"
      },
      {
        "entry": "ג",
        "zip": 8428297,
        "pos": "31.2507770076416,34.7856406771347"
      }
    ],
    "n": 67
  },
  {
    "zip": 8426401,
    "pos": "31.2507146397383,34.785922264303",
    "entries": [
      {
        "entry": "ג",
        "zip": 8426402,
        "pos": "31.2507146397383,34.785922264303"
      },
      {
        "entry": "",
        "zip": 8428298,
        "pos": "31.2507146397383,34.785922264303"
      },
      {
        "entry": "א",
        "zip": 8428299,
        "pos": "31.2507146397383,34.785922264303"
      }
    ],
    "n": 69
  },
  {
    "zip": 8426403,
    "pos": "31.2507810330789,34.78617575562",
    "entries": [
      {
        "entry": "א",
        "zip": 8426404,
        "pos": "31.2507810330789,34.78617575562"
      },
      {
        "entry": "ב",
        "zip": 8426405,
        "pos": "31.2507810330789,34.78617575562"
      },
      {
        "entry": "ג",
        "zip": 8426406,
        "pos": "31.2507810330789,34.78617575562"
      }
    ],
    "n": 71
  },
  {
    "zip": 8426407,
    "pos": "31.2509580407707,34.7863970380162",
    "entries": [
      {
        "entry": "א",
        "zip": 8426408,
        "pos": "31.2509580407707,34.7863970380162"
      },
      {
        "entry": "ב",
        "zip": 8426409,
        "pos": "31.2509580407707,34.7863970380162"
      },
      {
        "entry": "ג",
        "zip": 8426410,
        "pos": "31.2509580407707,34.7863970380162"
      }
    ],
    "n": 73
  }
]