[
  {
    "name": "אבנאא יעקב",
    "symbol": 120,
    "houses": 0
  },
  {
    "name": "אל-ח'לה",
    "symbol": 140,
    "houses": 0
  },
  {
    "name": "אל-לורי",
    "symbol": 135,
    "houses": 0
  },
  {
    "name": "אלבאבור",
    "symbol": 112,
    "houses": 0
  },
  {
    "name": "אלביאדר",
    "symbol": 104,
    "houses": 0
  },
  {
    "name": "אלבלאטה",
    "symbol": 119,
    "houses": 0
  },
  {
    "name": "אלברכה",
    "symbol": 106,
    "houses": 0
  },
  {
    "name": "אלג'בל",
    "symbol": 130,
    "houses": 0
  },
  {
    "name": "אלג'מאל",
    "symbol": 138,
    "houses": 0
  },
  {
    "name": "אלג'רף",
    "symbol": 133,
    "houses": 0
  },
  {
    "name": "אלורדה",
    "symbol": 128,
    "houses": 0
  },
  {
    "name": "אלזיר",
    "symbol": 134,
    "houses": 0
  },
  {
    "name": "אלזיתון",
    "symbol": 123,
    "houses": 0
  },
  {
    "name": "אלזנאר",
    "symbol": 101,
    "houses": 0
  },
  {
    "name": "אלח'לוה",
    "symbol": 125,
    "houses": 0
  },
  {
    "name": "אלחואכיר",
    "symbol": 124,
    "houses": 0
  },
  {
    "name": "אלחמרה",
    "symbol": 122,
    "houses": 0
  },
  {
    "name": "אלטיון",
    "symbol": 102,
    "houses": 0
  },
  {
    "name": "אלטין",
    "symbol": 111,
    "houses": 0
  },
  {
    "name": "אלכרם אלעמיק",
    "symbol": 108,
    "houses": 0
  },
  {
    "name": "אלמזבלה",
    "symbol": 139,
    "houses": 0
  },
  {
    "name": "אלמקאבר",
    "symbol": 116,
    "houses": 0
  },
  {
    "name": "אלנס'ב",
    "symbol": 131,
    "houses": 0
  },
  {
    "name": "אלנקאר",
    "symbol": 114,
    "houses": 0
  },
  {
    "name": "אלס'חירה",
    "symbol": 126,
    "houses": 0
  },
  {
    "name": "אלסהל",
    "symbol": 118,
    "houses": 0
  },
  {
    "name": "אלסרוה",
    "symbol": 121,
    "houses": 0
  },
  {
    "name": "אלעטאר",
    "symbol": 5012,
    "houses": 0
  },
  {
    "name": "אלעין",
    "symbol": 113,
    "houses": 0
  },
  {
    "name": "אלקובה",
    "symbol": 109,
    "houses": 0
  },
  {
    "name": "אלתנור",
    "symbol": 129,
    "houses": 0
  },
  {
    "name": "דהר אלביאד",
    "symbol": 103,
    "houses": 0
  },
  {
    "name": "דהר אלמגארה",
    "symbol": 110,
    "houses": 0
  },
  {
    "name": "ואדי חמיד",
    "symbol": 127,
    "houses": 0
  },
  {
    "name": "יוסף אלגריב",
    "symbol": 117,
    "houses": 0
  },
  {
    "name": "מסרב אלחסאדין",
    "symbol": 107,
    "houses": 0
  },
  {
    "name": "מע'ארת עובה",
    "symbol": 105,
    "houses": 0
  },
  {
    "name": "ראס אלמרג'",
    "symbol": 115,
    "houses": 0
  }
]